rsbmenu.py
rsbmenu-2.2.5.dist-info/METADATA
rsbmenu-2.2.5.dist-info/WHEEL
rsbmenu-2.2.5.dist-info/top_level.txt
rsbmenu-2.2.5.dist-info/RECORD
