Metadata-Version: 2.1
Name: rsbmenu
Version: 2.2.5
Summary: This is a normal Menu widget
Home-page: UNKNOWN
Author: R.Raja subramanian
Author-email: rajasubramanian.r1@gmail.com
License: UNKNOWN
Platform: UNKNOWN
